{"source": "Gratistravtips ABCD", "url": "https://www.gratistravtips.se/romme/2026-03-20/v65", "legs": {"1": [{"nr": 1, "name": "Red Hot Roadster", "rank": "D", "pts": 2}, {"nr": 2, "name": "Call Me Gleipner", "rank": "B", "pts": 10}, {"nr": 4, "name": "Herakles Zet", "rank": "C", "pts": 8}, {"nr": 5, "name": "Västerbo Exciting", "rank": "C", "pts": 6}, {"nr": 6, "name": "Västerbo Tramp", "rank": "C", "pts": 5}], "2": [{"nr": 1, "name": "Sörbo Doris", "rank": "C", "pts": 12}, {"nr": 2, "name": "Solianne", "rank": "D", "pts": 5}, {"nr": 3, "name": "Eldfaksa E.B.", "rank": "D", "pts": 2}, {"nr": 4, "name": "Spika Af Sola", "rank": "C", "pts": 14}, {"nr": 5, "name": "Ziken En L.K.", "rank": "B", "pts": 18}, {"nr": 6, "name": "Löset Odin*", "rank": "A", "pts": 25}, {"nr": 8, "name": "Olsims Robin", "rank": "B", "pts": 17}, {"nr": 9, "name": "Klack Artur", "rank": "D", "pts": 9}, {"nr": 10, "name": "Ängsprinsen", "rank": "A", "pts": 23}, {"nr": 11, "name": "Gåhejamäre", "rank": "D", "pts": 0}, {"nr": 12, "name": "Tvea Kisen", "rank": "D", "pts": 6}, {"nr": 13, "name": "Hubert", "rank": "C", "pts": 10}, {"nr": 14, "name": "Illbattingen", "rank": "B", "pts": 20}], "3": [{"nr": 1, "name": "Teaberry", "rank": "C", "pts": 6}, {"nr": 2, "name": "Putitinneutral", "rank": "C", "pts": 10}, {"nr": 3, "name": "Rover Tooma", "rank": "C", "pts": 7}, {"nr": 4, "name": "Secret Ale*", "rank": "C", "pts": 10}, {"nr": 5, "name": "Rocket Blaster", "rank": "D", "pts": 4}, {"nr": 6, "name": "Augustus Woodland", "rank": "D", "pts": 4}, {"nr": 7, "name": "Olympia Sting", "rank": "B", "pts": 13}, {"nr": 8, "name": "Can'T Be Ruled", "rank": "B", "pts": 12}], "4": [{"nr": 1, "name": "Helin Prinsen*", "rank": "B", "pts": 19}, {"nr": 2, "name": "Fjord Jenta*", "rank": "B", "pts": 23}, {"nr": 3, "name": "B.G.Buller Gunhild", "rank": "C", "pts": 18}, {"nr": 4, "name": "Nons Ville", "rank": "D", "pts": 6}, {"nr": 5, "name": "Thule Bosse", "rank": "D", "pts": 4}, {"nr": 6, "name": "P.D.Viribus", "rank": "C", "pts": 13}, {"nr": 7, "name": "Troll Borken N.O.", "rank": "D", "pts": 9}, {"nr": 8, "name": "Hagaz William", "rank": "C", "pts": 14}, {"nr": 9, "name": "Bato Odin", "rank": "D", "pts": 8}, {"nr": 10, "name": "Hade Tur", "rank": "A", "pts": 29}, {"nr": 11, "name": "Trönö Borken", "rank": "D", "pts": 12}, {"nr": 12, "name": "Sjöli Albert*", "rank": "C", "pts": 18}, {"nr": 13, "name": "Vima Odin", "rank": "C", "pts": 14}, {"nr": 14, "name": "Best Rauen*", "rank": "A", "pts": 25}, {"nr": 15, "name": "Slotts Stark", "rank": "B", "pts": 19}], "5": [{"nr": 1, "name": "Charming Laura*", "rank": "B", "pts": 18}, {"nr": 2, "name": "Vida Roc", "rank": "B", "pts": 15}, {"nr": 3, "name": "Cassiopeja Af Teda", "rank": "D", "pts": 3}, {"nr": 4, "name": "Sign Of Times", "rank": "B", "pts": 18}, {"nr": 5, "name": "Fixa Vendil", "rank": "D", "pts": 8}, {"nr": 6, "name": "Pannacotta Doc", "rank": "D", "pts": 8}, {"nr": 7, "name": "Cha Cha Vendil", "rank": "D", "pts": 1}, {"nr": 8, "name": "Gosa Gosing", "rank": "C", "pts": 9}, {"nr": 9, "name": "Tacky Sugar", "rank": "B", "pts": 18}, {"nr": 10, "name": "Minerva Sisu*", "rank": "B", "pts": 15}], "6": [{"nr": 1, "name": "Mezcal Teorvici", "rank": "B", "pts": 19}, {"nr": 2, "name": "Googoo Gone", "rank": "C", "pts": 16}, {"nr": 3, "name": "Aberama Gold", "rank": "B", "pts": 22}, {"nr": 4, "name": "Qixi Roc", "rank": "D", "pts": 7}, {"nr": 5, "name": "Nonstop Käll", "rank": "D", "pts": 4}, {"nr": 6, "name": "Who'S The Winner", "rank": "C", "pts": 15}, {"nr": 7, "name": "Brilliant Kid", "rank": "A", "pts": 25}, {"nr": 8, "name": "Andy Gel", "rank": "C", "pts": 17}, {"nr": 9, "name": "Any Given Sunday", "rank": "B", "pts": 18}, {"nr": 10, "name": "Gentleman Sisu", "rank": "D", "pts": 1}, {"nr": 11, "name": "Thanator", "rank": "D", "pts": 3}, {"nr": 12, "name": "He'S From Heaven", "rank": "B", "pts": 22}, {"nr": 13, "name": "Like A Monster", "rank": "D", "pts": 7}]}}