{"source": "Gratistravtips ABCD", "url": "https://www.gratistravtips.se/romme/2026-03-13/v64", "legs": {"1": [{"nr": 1, "name": "Fazimo Trot*", "rank": "D", "pts": 8}, {"nr": 2, "name": "Juliette B.", "rank": "D", "pts": 9}, {"nr": 3, "name": "Los Del Rio Sisu", "rank": "A", "pts": 21}, {"nr": 4, "name": "Oktan Håleryd", "rank": "D", "pts": 3}, {"nr": 5, "name": "Ajlexes Oyecomo Va", "rank": "A", "pts": 21}, {"nr": 6, "name": "Gosa Gosing", "rank": "C", "pts": 14}, {"nr": 7, "name": "Sandsjöns Avicii", "rank": "D", "pts": 7}, {"nr": 8, "name": "Nybys Leia", "rank": "C", "pts": 12}, {"nr": 9, "name": "Overstime", "rank": "D", "pts": 1}, {"nr": 10, "name": "Make My Trip V.S.", "rank": "B", "pts": 18}, {"nr": 11, "name": "Dragonfly*", "rank": "B", "pts": 17}], "2": [{"nr": 1, "name": "Freja Hammering", "rank": "A", "pts": 21}, {"nr": 2, "name": "M.T.Vanessa", "rank": "D", "pts": 2}, {"nr": 3, "name": "Suger Sweet Melody", "rank": "D", "pts": 6}, {"nr": 4, "name": "Peron Evita Boko", "rank": "D", "pts": 9}, {"nr": 5, "name": "Fresh Breeze", "rank": "B", "pts": 16}, {"nr": 6, "name": "Dream From Above", "rank": "C", "pts": 13}, {"nr": 7, "name": "Uno Di Troppo", "rank": "D", "pts": 8}, {"nr": 8, "name": "Lavazza Sisu", "rank": "D", "pts": 8}, {"nr": 10, "name": "Sandsjöns Aquila", "rank": "C", "pts": 11}, {"nr": 11, "name": "Tiffany M.M.", "rank": "D", "pts": 5}, {"nr": 12, "name": "Little Eva", "rank": "A", "pts": 21}, {"nr": 13, "name": "Kiss My Feet", "rank": "B", "pts": 16}, {"nr": 14, "name": "Solkattens Raze", "rank": "C", "pts": 15}, {"nr": 15, "name": "Giant Koala", "rank": "A", "pts": 23}], "3": [{"nr": 1, "name": "Joners Majah", "rank": "D", "pts": 6}, {"nr": 2, "name": "Passarella Boko", "rank": "C", "pts": 9}, {"nr": 3, "name": "D'Artagnan Awec", "rank": "C", "pts": 12}, {"nr": 4, "name": "Brionne", "rank": "B", "pts": 14}, {"nr": 5, "name": "Obiwan Keeper", "rank": "B", "pts": 18}, {"nr": 6, "name": "Emerald Broline", "rank": "D", "pts": 5}, {"nr": 7, "name": "Burn It Down Ås", "rank": "C", "pts": 12}, {"nr": 8, "name": "Knuff", "rank": "C", "pts": 9}, {"nr": 9, "name": "Knaborgs Jarl", "rank": "D", "pts": 1}, {"nr": 10, "name": "The Pretender", "rank": "B", "pts": 15}, {"nr": 11, "name": "Django Mango", "rank": "C", "pts": 11}], "4": [{"nr": 1, "name": "Kalida*", "rank": "B", "pts": 18}, {"nr": 2, "name": "Yngve C.G.", "rank": "D", "pts": 2}, {"nr": 3, "name": "Lannem Sokken*", "rank": "A", "pts": 24}, {"nr": 4, "name": "Lystad Loke", "rank": "D", "pts": 4}, {"nr": 5, "name": "Mana Figg", "rank": "D", "pts": 5}, {"nr": 6, "name": "Lillprinsen", "rank": "B", "pts": 19}, {"nr": 8, "name": "Pegasus", "rank": "D", "pts": 10}, {"nr": 9, "name": "K.A.Viktor", "rank": "C", "pts": 11}, {"nr": 10, "name": "Ingen*", "rank": "D", "pts": 10}, {"nr": 11, "name": "Mjölner Ty*", "rank": "A", "pts": 26}, {"nr": 12, "name": "Eirik Af Sola*", "rank": "C", "pts": 16}], "5": [{"nr": 1, "name": "Girls Runtheworld", "rank": "D", "pts": 9}, {"nr": 2, "name": "Oliver Schermer", "rank": "D", "pts": 9}, {"nr": 3, "name": "Sharp Object", "rank": "D", "pts": 9}, {"nr": 4, "name": "Mayflower", "rank": "D", "pts": 4}, {"nr": 5, "name": "Hector Godiva", "rank": "D", "pts": 8}, {"nr": 6, "name": "Behind Hotshot", "rank": "D", "pts": 7}, {"nr": 7, "name": "Geisha Road Grif*", "rank": "A", "pts": 22}, {"nr": 8, "name": "Denaro Diabolik", "rank": "B", "pts": 19}, {"nr": 9, "name": "Pannacotta Doc", "rank": "B", "pts": 17}, {"nr": 10, "name": "Bull Woodland", "rank": "C", "pts": 15}, {"nr": 11, "name": "Bill Woodland", "rank": "D", "pts": 5}, {"nr": 12, "name": "Justcantgetenough", "rank": "C", "pts": 15}], "6": [{"nr": 1, "name": "Belgique", "rank": "C", "pts": 12}, {"nr": 3, "name": "Picobello", "rank": "A", "pts": 18}, {"nr": 4, "name": "Mr Birkenstock", "rank": "D", "pts": 2}, {"nr": 5, "name": "Jes Angel", "rank": "C", "pts": 8}, {"nr": 6, "name": "Gordini Brick", "rank": "B", "pts": 13}, {"nr": 7, "name": "Drizzle", "rank": "C", "pts": 8}, {"nr": 8, "name": "Babaris", "rank": "D", "pts": 2}, {"nr": 9, "name": "Express Cash", "rank": "D", "pts": 5}, {"nr": 10, "name": "Sparky'S Dream", "rank": "B", "pts": 15}, {"nr": 11, "name": "Ecu De Mieloui*", "rank": "D", "pts": 6}]}}